LICENSE
README.md
setup.py
fast_weather/__init__.py
fast_weather/__version__.py
fast_weather/weather.py
fast_weather.egg-info/PKG-INFO
fast_weather.egg-info/SOURCES.txt
fast_weather.egg-info/dependency_links.txt
fast_weather.egg-info/requires.txt
fast_weather.egg-info/top_level.txt