Metadata-Version: 2.1
Name: fast-weather
Version: 0.1.2
Summary: 天气查询
Home-page: https://www.wolai.com/sunxianyong/u5SSoLUbfmHb2aELs5jPGn
Author: Qin Qiu
Author-email: sxy122333@outlook.com
License: MIT
Classifier: License :: OSI Approved :: MIT License
Classifier: Programming Language :: Python
Classifier: Programming Language :: Python :: 3
Classifier: Programming Language :: Python :: 3.6
Classifier: Programming Language :: Python :: Implementation :: CPython
Classifier: Programming Language :: Python :: Implementation :: PyPy
Requires-Python: >=3.6.0
License-File: LICENSE
